main.py
mseep_yfinance_trader-0.1.1.dist-info/METADATA
mseep_yfinance_trader-0.1.1.dist-info/WHEEL
mseep_yfinance_trader-0.1.1.dist-info/entry_points.txt
mseep_yfinance_trader-0.1.1.dist-info/top_level.txt
mseep_yfinance_trader-0.1.1.dist-info/RECORD
