Metadata-Version: 2.4
Name: mseep-yfinance-trader
Version: 0.1.1
Summary: YFinance Trader MCP Tool for Claude Desktop
Author-email: mseep <support@skydeck.ai>
License: MIT
Requires-Python: >=3.10
Requires-Dist: yfinance>=0.2.36
Requires-Dist: fastapi>=0.103.1
Requires-Dist: uvicorn>=0.23.2
Requires-Dist: pydantic>=2.4.2
Requires-Dist: requests>=2.31.0
Requires-Dist: pandas>=2.1.0
Provides-Extra: dev
Requires-Dist: pytest>=7.0.0; extra == "dev"
Requires-Dist: black>=23.1.0; extra == "dev"
Requires-Dist: isort>=5.12.0; extra == "dev"
